gtw_apu_ppt/__init__.py
gtw_apu_ppt/run_app.py
gtw_apu_ppt/aplikasi/__init__.py
gtw_apu_ppt/aplikasi/utils.py
gtw_apu_ppt/aplikasi/rekap/__init__.py
gtw_apu_ppt/aplikasi/rekap/controller.py
gtw_apu_ppt/aplikasi/rekap/routes.py
gtw_apu_ppt-0.0.1.dist-info/LICENSE
gtw_apu_ppt-0.0.1.dist-info/METADATA
gtw_apu_ppt-0.0.1.dist-info/WHEEL
gtw_apu_ppt-0.0.1.dist-info/top_level.txt
gtw_apu_ppt-0.0.1.dist-info/RECORD
